ssh2net/__init__.py
ssh2net/base.py
ssh2net/channel.py
ssh2net/decorators.py
ssh2net/exceptions.py
ssh2net/helper.py
ssh2net/netmiko_compatibility.py
ssh2net/session.py
ssh2net/session_miko.py
ssh2net/session_ssh2.py
ssh2net/ssh_config.py
ssh2net/community/__init__.py
ssh2net/core/__init__.py
ssh2net/core/driver.py
ssh2net/core/arista_eos/__init__.py
ssh2net/core/arista_eos/driver.py
ssh2net/core/cisco_iosxe/__init__.py
ssh2net/core/cisco_iosxe/driver.py
ssh2net/core/cisco_iosxr/__init__.py
ssh2net/core/cisco_iosxr/driver.py
ssh2net/core/cisco_nxos/__init__.py
ssh2net/core/cisco_nxos/driver.py
ssh2net/core/juniper_junos/__init__.py
ssh2net/core/juniper_junos/driver.py
ssh2net/core/juniper_junos/helper.py
tests/__init__.py
tests/functional/__init__.py
tests/functional/base_functional_tests.py
tests/unit/__init__.py
tests/unit/ext_test_funcs.py
tests/unit/test_base.py
tests/unit/test_channel.py
tests/unit/test_core_driver.py
tests/unit/test_decorators.py
tests/unit/test_helper.py
tests/unit/test_netmiko_compatibility.py
tests/unit/test_session.py
tests/unit/test_ssh_config.py
tests/unit/drivers/__init__.py
tests/unit/drivers/base_driver_unit_tests.py
tests/unit/drivers/core/__init__.py
tests/unit/drivers/core/test_core_arista_eos_driver.py
tests/unit/drivers/core/test_core_cisco_iosxe_driver.py
tests/unit/drivers/core/test_core_cisco_iosxr_driver.py
tests/unit/drivers/core/test_core_cisco_nxos_driver.py
tests/unit/drivers/core/test_core_juniper_junos_driver.py
ssh2net-2020.1.10.dist-info/LICENSE
ssh2net-2020.1.10.dist-info/METADATA
ssh2net-2020.1.10.dist-info/WHEEL
ssh2net-2020.1.10.dist-info/top_level.txt
ssh2net-2020.1.10.dist-info/RECORD
