Metadata-Version: 2.1
Name: ssh2net
Version: 2020.1.10
Summary: SSH client for network devices built on ssh2-python
Home-page: https://github.com/carlmontanari/ssh2net
Author: Carl Montanari
Author-email: carl.r.montanari@gmail.com
License: UNKNOWN
Platform: UNKNOWN
Classifier: License :: OSI Approved :: MIT License
Classifier: Programming Language :: Python :: 3
Classifier: Programming Language :: Python :: 3.6
Classifier: Programming Language :: Python :: 3.7
Classifier: Programming Language :: Python :: 3.8
Classifier: Operating System :: POSIX :: Linux
Classifier: Operating System :: MacOS
Requires-Python: >=3.6
Requires-Dist: ssh2-python (>=0.18.0-1)
Provides-Extra: paramiko
Requires-Dist: paramiko (>=2.6.0) ; extra == 'paramiko'
Provides-Extra: textfsm
Requires-Dist: textfsm (>=1.1.0) ; extra == 'textfsm'
Requires-Dist: ntc-templates (>=1.1.0) ; extra == 'textfsm'
